{
    "plan": {
        "cartservice": {
            "release_time": 1695443587,
            "target_replica": 3,
            "process": {
                "1695443587": {
                    "v1": 2,
                    "v2": 1,
                    "release_pod": [
                        "cartservice-v2-54455997f4-vh6bn"
                    ],
                    "delete_pod": [
                        "cartservice-v1-685f9dd56f-thxgl"
                    ],
                    "release_complete_time": "2023-09-23 04:34:12",
                    "release_complete_timestamp": 1695443652
                },
                "1695444583": {
                    "v1": 1,
                    "v2": 2,
                    "release_pod": [
                        "cartservice-v2-54455997f4-hfxgj"
                    ],
                    "delete_pod": [
                        "cartservice-v1-685f9dd56f-7z8vl"
                    ],
                    "release_complete_time": "2023-09-23 04:50:38",
                    "release_complete_timestamp": 1695444638
                },
                "1695443979": {
                    "v1": 0,
                    "v2": 3,
                    "release_pod": [
                        "cartservice-v2-54455997f4-lsvf9"
                    ],
                    "delete_pod": [
                        "cartservice-v1-685f9dd56f-t5zxp"
                    ],
                    "release_complete_time": "2023-09-23 04:51:33",
                    "release_complete_timestamp": 1695444693
                }
            },
            "fault": null
        },
        "emailservice": {
            "release_time": 1695443623,
            "target_replica": 3,
            "process": {
                "1695443623": {
                    "v1": 2,
                    "v2": 1,
                    "release_pod": [
                        "emailservice-v2-56777855c6-2kvhw"
                    ],
                    "delete_pod": [
                        "emailservice-v1-74655757-nc5hv"
                    ],
                    "release_complete_time": "2023-09-23 04:34:48",
                    "release_complete_timestamp": 1695443688
                },
                "1695444749": {
                    "v1": 1,
                    "v2": 2,
                    "release_pod": [
                        "emailservice-v2-56777855c6-54bjx"
                    ],
                    "delete_pod": [
                        "emailservice-v1-74655757-6dzvt"
                    ],
                    "release_complete_time": "2023-09-23 04:53:24",
                    "release_complete_timestamp": 1695444804
                },
                "1695444115": {
                    "v1": 0,
                    "v2": 3,
                    "release_pod": [
                        "emailservice-v2-56777855c6-mv9gc"
                    ],
                    "delete_pod": [
                        "emailservice-v1-74655757-bwt9d"
                    ],
                    "release_complete_time": "2023-09-23 04:54:19",
                    "release_complete_timestamp": 1695444859
                }
            },
            "fault": null
        },
        "productcatalogservice": {
            "release_time": 1695443495,
            "target_replica": 5,
            "process": {
                "1695443495": {
                    "v1": 4,
                    "v2": 1,
                    "release_pod": [
                        "productcatalogservice-v2-6745fcd455-5nc2n"
                    ],
                    "delete_pod": [
                        "productcatalogservice-v1-7bb89585b4-mfl22"
                    ],
                    "release_complete_time": "2023-09-23 04:32:40",
                    "release_complete_timestamp": 1695443560
                },
                "1695444650": {
                    "v1": 3,
                    "v2": 2,
                    "release_pod": [
                        "productcatalogservice-v2-6745fcd455-ddv4v"
                    ],
                    "delete_pod": [
                        "productcatalogservice-v1-7bb89585b4-ckhbb"
                    ],
                    "release_complete_time": "2023-09-23 04:51:45",
                    "release_complete_timestamp": 1695444705
                },
                "1695443833": {
                    "v1": 2,
                    "v2": 3,
                    "release_pod": [
                        "productcatalogservice-v2-6745fcd455-zjrn6"
                    ],
                    "delete_pod": [
                        "productcatalogservice-v1-7bb89585b4-g54w2"
                    ],
                    "release_complete_time": "2023-09-23 04:52:40",
                    "release_complete_timestamp": 1695444760
                },
                "1695444042": {
                    "v1": 1,
                    "v2": 4,
                    "release_pod": [
                        "productcatalogservice-v2-6745fcd455-pqztz"
                    ],
                    "delete_pod": [
                        "productcatalogservice-v1-7bb89585b4-kq8fr"
                    ],
                    "release_complete_time": "2023-09-23 04:53:35",
                    "release_complete_timestamp": 1695444815
                },
                "1695443952": {
                    "v1": 0,
                    "v2": 5,
                    "release_pod": [
                        "productcatalogservice-v2-6745fcd455-66p2c"
                    ],
                    "delete_pod": [
                        "productcatalogservice-v1-7bb89585b4-xvfm4"
                    ],
                    "release_complete_time": "2023-09-23 04:54:31",
                    "release_complete_timestamp": 1695444871
                }
            },
            "fault": null
        }
    },
    "fault": "redis",
    "fault_release_service": "cartservice",
    "normal_service_list": [
        "emailservice",
        "productcatalogservice"
    ],
    "experiment_time": "2023-09-23 04:16:04",
    "before_change_list": [
        "adservice-v1-59dcc9f97-5hkdc",
        "adservice-v1-59dcc9f97-77n6j",
        "adservice-v1-59dcc9f97-ff7k8",
        "adservice-v1-59dcc9f97-qr25s",
        "adservice-v1-59dcc9f97-xr694",
        "cartservice-v1-685f9dd56f-7z8vl",
        "cartservice-v1-685f9dd56f-t5zxp",
        "cartservice-v1-685f9dd56f-thxgl",
        "checkoutservice-v1-857f69df7f-bk84s",
        "checkoutservice-v1-857f69df7f-nsq4m",
        "checkoutservice-v1-857f69df7f-x9w7r",
        "currencyservice-v1-57684b474b-c9tvm",
        "currencyservice-v1-57684b474b-l4sq7",
        "currencyservice-v1-57684b474b-t96hk",
        "emailservice-v1-74655757-6dzvt",
        "emailservice-v1-74655757-bwt9d",
        "emailservice-v1-74655757-nc5hv",
        "frontend-v1-684ff8b787-g9nmd",
        "loadgenerator-75f659cdb5-5b77s",
        "loadgenerator-75f659cdb5-ns6kl",
        "loadgenerator-75f659cdb5-tplvj",
        "paymentservice-v1-65d5f78d47-5swhd",
        "paymentservice-v1-65d5f78d47-mckjf",
        "paymentservice-v1-65d5f78d47-z9xhk",
        "productcatalogservice-v1-7bb89585b4-ckhbb",
        "productcatalogservice-v1-7bb89585b4-g54w2",
        "productcatalogservice-v1-7bb89585b4-kq8fr",
        "productcatalogservice-v1-7bb89585b4-mfl22",
        "productcatalogservice-v1-7bb89585b4-xvfm4",
        "recommendationservice-v1-5b769cd779-8vv5m",
        "recommendationservice-v1-5b769cd779-cpv8h",
        "recommendationservice-v1-5b769cd779-f4v6r",
        "recommendationservice-v1-5b769cd779-v5srb",
        "recommendationservice-v1-5b769cd779-x7pcr",
        "shippingservice-v1-85764c6c94-8c6gp",
        "shippingservice-v1-85764c6c94-959wj",
        "shippingservice-v1-85764c6c94-bvns7"
    ],
    "experiemnt_end_time": "2023-09-23 04:54:31",
    "detect_timestamp": 1695443663,
    "detect_time": "2023-09-23 04:34:23",
    "GIED_result": "checkoutservice",
    "Microscope_result": "checkoutservice",
    "Microrca_result": "frontend",
    "spicious_set_microscope": [
        "shippingservice",
        "checkoutservice",
        "paymentservice",
        "emailservice",
        "currencyservice",
        "frontend",
        "recommendationservice",
        "adservice",
        "cartservice",
        "productcatalogservice"
    ]
}