{
    "module_name": "emailservice",
    "create_time": 1695441048,
    "host_list_change": [
        {
            "ip_addr": "emailservice-v1-74655757-8fgd9",
            "alert_metric": {
                "checkoutservice_emailservice": {
                    "system_fail": {
                        "points": [
                            100,
                            100,
                            100,
                            100,
                            100,
                            100,
                            100,
                            100,
                            100,
                            100,
                            100,
                            100,
                            100,
                            100,
                            100,
                            100,
                            100,
                            100
                        ],
                        "diff_points": [
                            100.0,
                            100.0,
                            100.0,
                            100.0,
                            100.0,
                            100.0,
                            100.0,
                            100.0,
                            100.0,
                            100.0,
                            100.0,
                            100.0,
                            100.0,
                            100.0,
                            100.0,
                            100.0
                        ]
                    }
                }
            },
            "before_change_metric": {
                "checkoutservice_emailservice": {
                    "system_fail": {
                        "points": [
                            100.0,
                            100.0,
                            100.0,
                            100.0,
                            100.0,
                            100.0,
                            100.0,
                            100.0,
                            100.0,
                            100.0,
                            100.0,
                            100.0,
                            100.0,
                            100.0,
                            100.0,
                            100.0
                        ],
                        "diff_points": [
                            100.0,
                            100.0,
                            100.0,
                            100.0,
                            100.0,
                            100.0,
                            100.0,
                            100.0,
                            100.0,
                            100.0,
                            100.0,
                            100.0,
                            100.0,
                            100.0,
                            100.0,
                            100.0
                        ]
                    }
                }
            },
            "resource": {
                "cpu": [
                    4.340362548828125,
                    4.340362548828125,
                    4.340362548828125,
                    4.340362548828125,
                    4.340362548828125,
                    4.340362548828125,
                    4.340362548828125,
                    4.340362548828125,
                    4.340362548828125,
                    4.340362548828125,
                    4.340362548828125,
                    4.340362548828125,
                    4.340362548828125,
                    4.340362548828125,
                    4.340362548828125,
                    4.340362548828125,
                    4.340362548828125,
                    4.340362548828125
                ],
                "memory": [
                    14.481128092480787,
                    13.602568435252426,
                    13.590057911018775,
                    14.592745851447155,
                    13.822064657751088,
                    13.683722107388109,
                    13.663466824509818,
                    13.840961822379171,
                    13.169037940405516,
                    13.736192891246455,
                    13.419327553417414,
                    13.800532251910115,
                    13.995437647826593,
                    13.407040284604044,
                    13.295824696452419,
                    14.843320505735402,
                    14.318970625573535,
                    13.939522097684664
                ]
            }
        }
    ],
    "host_list_old": [
        {
            "ip_addr": "emailservice-v1-74655757-bxcgv",
            "alert_metric": {
                "checkoutservice_emailservice": {
                    "system_fail": {
                        "points": [
                            100,
                            100,
                            100,
                            100,
                            100,
                            100,
                            100,
                            100,
                            100,
                            100,
                            100,
                            100,
                            100,
                            100,
                            100,
                            100,
                            100
                        ],
                        "diff_points": [
                            100.0,
                            100.0,
                            100.0,
                            100.0,
                            100.0,
                            100.0,
                            100.0,
                            100.0,
                            100.0,
                            100.0,
                            100.0,
                            100.0,
                            100.0,
                            100.0,
                            100.0,
                            100.0
                        ]
                    }
                }
            },
            "resource": {
                "cpu": [
                    4.370880126953125,
                    4.370880126953125,
                    4.370880126953125,
                    4.370880126953125,
                    4.370880126953125,
                    4.370880126953125,
                    4.370880126953125,
                    4.370880126953125,
                    4.370880126953125,
                    4.370880126953125,
                    4.370880126953125,
                    4.370880126953125,
                    4.370880126953125,
                    4.370880126953125,
                    4.370880126953125,
                    4.370880126953125,
                    4.370880126953125
                ],
                "memory": [
                    2.5767796539232,
                    2.498742243840424,
                    2.367827612128304,
                    2.918238993707667,
                    2.561844863729179,
                    2.591693183726252,
                    2.4184759828950075,
                    2.589349310773281,
                    2.5013617128309185,
                    2.613065326636565,
                    2.552923915324812,
                    2.4830131700442903,
                    2.7238821606870744,
                    2.5637803192167907,
                    2.544326612719816,
                    2.8015433652003763,
                    2.697156259175293
                ]
            }
        },
        {
            "ip_addr": "emailservice-v1-74655757-f4hn5",
            "alert_metric": {
                "checkoutservice_emailservice": {
                    "system_fail": {
                        "points": [
                            100,
                            100,
                            100,
                            100,
                            100,
                            100,
                            100,
                            100,
                            100,
                            100,
                            100,
                            100,
                            100,
                            100,
                            100,
                            100,
                            100,
                            100
                        ],
                        "diff_points": [
                            100.0,
                            100.0,
                            100.0,
                            100.0,
                            100.0,
                            100.0,
                            100.0,
                            100.0,
                            100.0,
                            100.0,
                            100.0,
                            100.0,
                            100.0,
                            100.0,
                            100.0,
                            100.0
                        ]
                    }
                }
            },
            "resource": {
                "cpu": [
                    4.354095458984375,
                    4.354095458984375,
                    4.354095458984375,
                    4.354095458984375,
                    4.354095458984375,
                    4.354095458984375,
                    4.354095458984375,
                    4.354095458984375,
                    4.354095458984375,
                    4.354095458984375,
                    4.354095458984375,
                    4.354095458984375,
                    4.354095458984375,
                    4.354095458984375,
                    4.354095458984375,
                    4.354095458984375,
                    4.354095458984375,
                    4.354095458984375
                ],
                "memory": [
                    1.8212267113252745,
                    1.7569546120038804,
                    1.661087866107358,
                    4.954748300435519,
                    4.573526957105589,
                    3.966597077255728,
                    2.394984326017457,
                    4.8642345494186126,
                    2.7455077308787823,
                    4.5899454371274295,
                    1.940854143126292,
                    4.827557480846433,
                    1.8695888577547115,
                    1.6684089483530284,
                    2.0010046885485355,
                    5.0321020595444965,
                    1.9737392322514369,
                    1.8231235626164355
                ]
            }
        }
    ],
    "deepth": 2,
    "downstream_list": [],
    "upstream_list": [
        "checkoutservice"
    ]
}