{
    "module_name": "emailservice",
    "create_time": 1695498528,
    "host_list_change": [
        {
            "ip_addr": "emailservice-v1-74655757-znxkh",
            "alert_metric": {
                "checkoutservice_emailservice": {
                    "system_fail": {
                        "points": [
                            100,
                            100,
                            100,
                            100,
                            100,
                            100,
                            100,
                            100,
                            100,
                            100,
                            100,
                            100,
                            100,
                            100,
                            100,
                            100,
                            100
                        ],
                        "diff_points": [
                            100.0,
                            100.0,
                            100.0,
                            100.0,
                            100.0,
                            100.0,
                            100.0,
                            100.0,
                            100.0,
                            100.0,
                            100.0,
                            100.0,
                            100.0,
                            100.0,
                            100.0,
                            100.0
                        ]
                    }
                }
            },
            "before_change_metric": {
                "checkoutservice_emailservice": {
                    "system_fail": {
                        "points": [
                            100.0,
                            100.0,
                            100.0,
                            100.0,
                            100.0,
                            100.0,
                            100.0,
                            100.0,
                            100.0,
                            100.0,
                            100.0,
                            100.0,
                            100.0,
                            100.0,
                            100.0,
                            100.0
                        ],
                        "diff_points": [
                            100.0,
                            100.0,
                            100.0,
                            100.0,
                            100.0,
                            100.0,
                            100.0,
                            100.0,
                            100.0,
                            100.0,
                            100.0,
                            100.0,
                            100.0,
                            100.0,
                            100.0,
                            100.0
                        ]
                    }
                }
            },
            "resource": {
                "cpu": [
                    4.2999267578125,
                    4.2999267578125,
                    4.2999267578125,
                    4.2999267578125,
                    4.2999267578125,
                    4.2999267578125,
                    4.2999267578125,
                    4.2999267578125,
                    4.2999267578125,
                    4.2999267578125,
                    4.2999267578125,
                    4.2999267578125,
                    4.2999267578125,
                    4.2999267578125,
                    4.2999267578125,
                    4.2999267578125,
                    4.2999267578125
                ],
                "memory": [
                    5.034430634852481,
                    5.210479835132842,
                    5.105079911075594,
                    4.4905660377463015,
                    4.449756752227128,
                    4.94277449378,
                    4.6969442578902685,
                    4.10372608260584,
                    4.153716925666228,
                    4.39657344419625,
                    4.471288955991294,
                    4.307163227644784,
                    4.0943032133463175,
                    4.066744927065824,
                    5.398263495668177,
                    5.993704092344742,
                    5.525465003966434
                ]
            }
        }
    ],
    "host_list_old": [
        {
            "ip_addr": "emailservice-v1-74655757-f4gn9",
            "alert_metric": {
                "checkoutservice_emailservice": {
                    "system_fail": {
                        "points": [
                            NaN,
                            NaN,
                            NaN,
                            NaN,
                            NaN,
                            NaN,
                            NaN,
                            NaN,
                            NaN,
                            NaN,
                            NaN,
                            NaN,
                            NaN,
                            NaN,
                            NaN,
                            NaN
                        ],
                        "diff_points": [
                            100.0,
                            100.0,
                            100.0,
                            100.0,
                            100.0,
                            100.0,
                            100.0,
                            100.0,
                            100.0,
                            100.0,
                            100.0,
                            100.0,
                            100.0,
                            100.0,
                            100.0,
                            100.0
                        ]
                    }
                }
            },
            "resource": {
                "cpu": [
                    4.34417724609375,
                    4.34417724609375,
                    4.34417724609375,
                    4.34417724609375,
                    4.34417724609375,
                    4.34417724609375,
                    4.34417724609375,
                    4.34417724609375,
                    4.34417724609375,
                    4.34417724609375,
                    4.34417724609375,
                    4.34417724609375,
                    4.34417724609375,
                    4.34417724609375,
                    4.34417724609375,
                    4.34417724609375
                ],
                "memory": [
                    2.1740951742634573,
                    2.152969757894163,
                    2.4052966812014853,
                    1.9478887399414613,
                    2.1018254898741984,
                    2.0794109033137165,
                    2.088390390901118,
                    1.9385362585874863,
                    2.091350175675022,
                    2.005526712441608,
                    2.05857740585923,
                    1.9378871588781488,
                    2.0742723318823653,
                    1.9217886451144641,
                    2.0808038517902805,
                    2.118218352305512
                ]
            }
        },
        {
            "ip_addr": "emailservice-v1-74655757-4qwwj",
            "alert_metric": {
                "checkoutservice_emailservice": {
                    "system_fail": {
                        "points": [
                            100.0,
                            NaN,
                            NaN,
                            NaN,
                            NaN,
                            NaN,
                            NaN,
                            NaN,
                            NaN,
                            NaN,
                            NaN,
                            NaN,
                            NaN,
                            NaN,
                            NaN,
                            NaN,
                            NaN
                        ],
                        "diff_points": [
                            100.0,
                            100.0,
                            100.0,
                            100.0,
                            100.0,
                            100.0,
                            100.0,
                            100.0,
                            100.0,
                            100.0,
                            100.0,
                            100.0,
                            100.0,
                            100.0,
                            100.0,
                            100.0
                        ]
                    }
                }
            },
            "resource": {
                "cpu": [
                    4.28619384765625,
                    4.28619384765625,
                    4.28619384765625,
                    4.28619384765625,
                    4.28619384765625,
                    4.28619384765625,
                    4.28619384765625,
                    4.28619384765625,
                    4.28619384765625,
                    4.28619384765625,
                    4.28619384765625,
                    4.28619384765625,
                    4.28619384765625,
                    4.28619384765625,
                    4.28619384765625,
                    4.28619384765625,
                    4.28619384765625
                ],
                "memory": [
                    5.071341897157621,
                    5.43829465822455,
                    5.161046487209309,
                    6.178028074284715,
                    5.638230978818769,
                    5.755002522305485,
                    5.911516322839061,
                    5.586357526886698,
                    4.864637985319121,
                    5.429446565656925,
                    5.303380222547083,
                    5.6847762196825755,
                    5.525210084043764,
                    5.836445264992774,
                    5.534807603538849,
                    5.381616999868599,
                    5.659504688211436
                ]
            }
        }
    ],
    "deepth": 1,
    "upstream_list": [
        "checkoutservice"
    ],
    "downstream_list": []
}